aipyapp/__init__.py
aipyapp/__main__.py
aipyapp/default.toml
aipyapp/default_en.toml
aipyapp/gui.py
aipyapp/main.py
aipyapp/publish.py
aipyapp/saas.py
aipyapp/wxgui.py
aipyapp/aipy/__init__.py
aipyapp/aipy/config.py
aipyapp/aipy/i18n.py
aipyapp/aipy/interface.py
aipyapp/aipy/llm.py
aipyapp/aipy/plugin.py
aipyapp/aipy/prompt.py
aipyapp/aipy/prompt.zh.py
aipyapp/aipy/prompt_en.py
aipyapp/aipy/qpython.py
aipyapp/aipy/runner.py
aipyapp/aipy/task.py
aipyapp/aipy/taskmgr.py
aipyapp/aipy/template.html
aipyapp/aipy/templates.py
aipyapp/aipy/utils.py
aipyapp_qpython-0.1.24.21.dist-info/METADATA
aipyapp_qpython-0.1.24.21.dist-info/WHEEL
aipyapp_qpython-0.1.24.21.dist-info/top_level.txt
aipyapp_qpython-0.1.24.21.dist-info/RECORD
